README.md
setup.py
debug_world_huajia/__init__.py
debug_world_huajia/print_str.py
debug_world_huajia.egg-info/PKG-INFO
debug_world_huajia.egg-info/SOURCES.txt
debug_world_huajia.egg-info/dependency_links.txt
debug_world_huajia.egg-info/top_level.txt